makeitlearn_isga/__init__.py
makeitlearn_isga-2.6.1.dist-info/LICENSE
makeitlearn_isga-2.6.1.dist-info/METADATA
makeitlearn_isga-2.6.1.dist-info/WHEEL
makeitlearn_isga-2.6.1.dist-info/top_level.txt
makeitlearn_isga-2.6.1.dist-info/RECORD
