Metadata-Version: 2.1
Name: makeitlearn-isga
Version: 2.6.1
Summary: This is a simple Machine Learning module
Home-page: UNKNOWN
Author: Achraf Mataich, ISGA Fes
Author-email: achraf.mataich@edu.isga.ma
License: UNKNOWN
Platform: UNKNOWN
Classifier: Programming Language :: Python :: 3
Classifier: License :: OSI Approved :: MIT License
Classifier: Operating System :: OS Independent
Requires-Dist: numpy
Requires-Dist: pandas
